simple_dag/__init__.py
simple_dag/_version.py
simple_dag/transforms.py
simple_dag/datahandlers/__init__.py
simple_dag/datahandlers/base_handler.py
simple_dag/datahandlers/binary_handler.py
simple_dag/datahandlers/directory_handler.py
simple_dag/datahandlers/filepath_handler.py
simple_dag/datahandlers/json_handler.py
simple_dag/datahandlers/multiple.py
simple_dag/datahandlers/pandas_handler.py
simple_dag/datahandlers/spark_handler.py
simple_dag/orchestrators/__init__.py
simple_dag/orchestrators/dagster.py
simple_dag/utils/__init__.py
simple_dag/utils/fsspec.py
simple_dag/utils/s3.py
simple_dag-1.0.5.dist-info/licenses/AUTHORS.rst
simple_dag-1.0.5.dist-info/licenses/LICENSE
simple_dag-1.0.5.dist-info/METADATA
simple_dag-1.0.5.dist-info/WHEEL
simple_dag-1.0.5.dist-info/entry_points.txt
simple_dag-1.0.5.dist-info/top_level.txt
simple_dag-1.0.5.dist-info/RECORD
