Metadata-Version: 2.4
Name: simple_dag
Version: 1.0.5
Summary: Create simple Pipelines with Python
Author-email: Tim Rohner <info@timrohner.ch>
License: MIT License
Project-URL: Source, https://github.com/leokster/simple_dag
Keywords: simple_dag
Classifier: Development Status :: 2 - Pre-Alpha
Classifier: Intended Audience :: Developers
Classifier: License :: OSI Approved :: MIT License
Classifier: Natural Language :: English
Classifier: Programming Language :: Python :: 3
Classifier: Programming Language :: Python :: 3.6
Classifier: Programming Language :: Python :: 3.7
Classifier: Programming Language :: Python :: 3.8
License-File: LICENSE
License-File: AUTHORS.rst
Requires-Dist: aiohttp<4,>=3.0.0
Requires-Dist: Click<=9,>=7.0
Requires-Dist: dagit<=2,>=1.3.7
Requires-Dist: dagster<=2,>=1.3.7
Requires-Dist: matplotlib<=4,>=3.4.2
Requires-Dist: pandas<=3,>=2.0.1
Requires-Dist: requests<3,>=2.0.0
Provides-Extra: dev
Requires-Dist: black<=24.4.2,>=21.7b0; extra == "dev"
Requires-Dist: tox<=4.25.0,>=3.14.0; extra == "dev"
Requires-Dist: twine<6,>=1.14.0; extra == "dev"
Dynamic: license-file
